cbe_verifier/__init__.py
cbe_verifier/detector.py
cbe_verifier/utils.py
cbe_verifier/verifier.py
CBE_verifier-1.1.1.dist-info/LICENSE
CBE_verifier-1.1.1.dist-info/METADATA
CBE_verifier-1.1.1.dist-info/WHEEL
CBE_verifier-1.1.1.dist-info/top_level.txt
CBE_verifier-1.1.1.dist-info/RECORD
