Metadata-Version: 2.1
Name: CBE_verifier
Version: 1.1.1
Summary: A transaction verification library for CBE.
Home-page: https://github.com/Zahir-Seid/CBE_verifier
Author: Zahir Seid
Author-email: Zahirseid101@gmail.com
Classifier: Programming Language :: Python :: 3
Classifier: License :: OSI Approved :: MIT License
Classifier: Operating System :: OS Independent
Requires-Python: >=3.6
License-File: LICENSE
Requires-Dist: easyocr
Requires-Dist: opencv-python
Requires-Dist: pillow
Requires-Dist: pyzbar
Requires-Dist: numpy
